cs_scan_bin_parser/__init__.py
cs_scan_bin_parser/bin_reader.py
cs_scan_bin_parser/duplicate_finder.py
cs_scan_bin_parser-0.1.0.dist-info/WHEEL
cs_scan_bin_parser-0.1.0.dist-info/entry_points.txt
cs_scan_bin_parser-0.1.0.dist-info/METADATA
cs_scan_bin_parser-0.1.0.dist-info/RECORD
