Metadata-Version: 2.3
Name: cs-scan-bin-parser
Version: 0.1.0
Summary: Add your description here
Author: Matthew Muller
Author-email: Matthew Muller <matthew.muller@epiroc.com>
Requires-Dist: numpy>=2.3.5
Requires-Python: >=3.14
